dgupdater/__init__.py
dgupdater/cli.py
dgupdater/bin/dgupdaterupdate_lin
dgupdater/bin/dgupdaterupdate_mac
dgupdater/bin/dgupdaterupdate_win.exe
dgupdater/cli_commands/__init__.py
dgupdater/cli_commands/commit/__init__.py
dgupdater/cli_commands/commit/commit.py
dgupdater/cli_commands/commit/func/__init__.py
dgupdater/cli_commands/commit/func/check_configuration_files_exists.py
dgupdater/cli_commands/commit/func/commit_changes.py
dgupdater/cli_commands/commit/func/create_chunks.py
dgupdater/cli_commands/commit/func/find_files.py
dgupdater/cli_commands/commit/func/update_version.py
dgupdater/cli_commands/commit/func/validate_version.py
dgupdater/cli_commands/init/__init__.py
dgupdater/cli_commands/init/init.py
dgupdater/cli_commands/init/func/__init__.py
dgupdater/cli_commands/init/func/check_app_exists.py
dgupdater/cli_commands/init/func/check_mongo_string.py
dgupdater/cli_commands/init/func/create_configuration_files.py
dgupdater/cli_commands/init/func/create_entry_in_mongodb.py
dgupdater/cli_commands/publish/__init__.py
dgupdater/cli_commands/publish/publish.py
dgupdater/cli_commands/publish/func/__init__.py
dgupdater/cli_commands/publish/func/check_release_files_exists.py
dgupdater/cli_commands/publish/func/publish_changes.py
dgupdater/cli_commands/update/__init__.py
dgupdater/cli_commands/update/update.py
dgupdater/cli_commands/update/func/__init__.py
dgupdater/cli_commands/update/func/acknowledge_update_to_client.py
dgupdater/cli_commands/update/func/delete_deprecated_files.py
dgupdater/functions/__init__.py
dgupdater/functions/check_update/__init__.py
dgupdater/functions/check_update/check_update.py
dgupdater/functions/check_update/func/__init__.py
dgupdater/functions/check_update/func/ask_to_be_updated.py
dgupdater/functions/check_update/func/check_update_from_db.py
dgupdater/functions/check_update/func/find_root_directory.py
dgupdater/functions/check_update/func/get_temp_file.py
dgupdater/functions/check_update/func/open_updater.py
dgupdater-1.2.1.dist-info/licenses/LICENSE
dgupdater-1.2.1.dist-info/METADATA
dgupdater-1.2.1.dist-info/WHEEL
dgupdater-1.2.1.dist-info/entry_points.txt
dgupdater-1.2.1.dist-info/top_level.txt
dgupdater-1.2.1.dist-info/RECORD
