Metadata-Version: 2.4
Name: dgupdater
Version: 1.2.1
Summary: A NO/LOW Code CLI based auto updation assistant tool for python applications
Author: DarkGlance
Author-email: darkglance.developer@gmail.com
Maintainer: DarkGlance
Maintainer-email: darkglance.developer@gmail.com
Project-URL: Github, https://github.com/Ashif4354/dgupdater
Keywords: dgupdater,auto updater,cli tool,python,pyupdater,python application,auto updation,auto update,update,cli,command line interface,no code,low code,no code tool,mongodb,pymongo,click
Classifier: Intended Audience :: Developers
Classifier: Development Status :: 5 - Production/Stable
Classifier: Programming Language :: Python :: 3.12
Classifier: License :: OSI Approved :: MIT License
Classifier: Operating System :: OS Independent
Classifier: Operating System :: Microsoft :: Windows
Classifier: Operating System :: Unix
Classifier: Operating System :: MacOS
Classifier: Environment :: Console
Classifier: Topic :: Utilities
Classifier: Topic :: Software Development :: Libraries :: Python Modules
Requires-Python: >=3.10
License-File: LICENSE
Requires-Dist: click>=7.0
Requires-Dist: pymongo
Requires-Dist: platformdirs
Requires-Dist: tqdm
Requires-Dist: rich
Dynamic: author
Dynamic: author-email
Dynamic: classifier
Dynamic: description
Dynamic: description-content-type
Dynamic: keywords
Dynamic: license-file
Dynamic: maintainer
Dynamic: maintainer-email
Dynamic: project-url
Dynamic: requires-dist
Dynamic: requires-python
Dynamic: summary
